pypi_build_pdm-0.0.2.dist-info/METADATA
pypi_build_pdm-0.0.2.dist-info/WHEEL
pypi_build_pdm-0.0.2.dist-info/entry_points.txt
pypi_build_pdm/__init__.py
pypi_build_pdm-0.0.2.dist-info/RECORD
